LICENSE
MANIFEST.in
README.rst
setup.py
src/ppnet/__init__.py
src/ppnet/common.py
src/ppnet/config.py
src/ppnet/pp_flow.py
src/ppnet/ppbeater.py
src/ppnet/ppchat.py
src/ppnet/ppl1node.py
src/ppnet/ppl2node.py
src/ppnet/ppl3node.py
src/ppnet/ppl4node.py
src/ppnet/stun_client.py
src/py_ppnet.egg-info/PKG-INFO
src/py_ppnet.egg-info/SOURCES.txt
src/py_ppnet.egg-info/dependency_links.txt
src/py_ppnet.egg-info/entry_points.txt
src/py_ppnet.egg-info/top_level.txt
src/test/__init__.py
src/test/mocknet.py
src/test/pseudo_net.py
src/test/run_test.py
src/test/test_pp_flow.py
src/test/test_ppl2node.py
src/test/test_ppmessage.py
src/test/test_ppnetnode.py
src/test/test_realnodes.py