Metadata-Version: 2.1
Name: py-ppnet
Version: 1.0.5.0
Summary: P2P network
Home-page: https://gitee.com/gonewind73/pytuntap
Author: gonewind.he
Author-email: gonewind.he@gmail.com
Maintainer: gonewind
Maintainer-email: gonewind.he@gmail.com
License: UNKNOWN
Platform: Linux
Platform: Windows
Classifier: Development Status :: 5 - Production/Stable
Classifier: Intended Audience :: Developers
Classifier: License :: OSI Approved :: MIT License
Classifier: Programming Language :: Python :: 3
Classifier: Topic :: Software Development :: Libraries :: Python Modules
Classifier: Topic :: System :: Networking
Requires-Python: >=3
